{"ret":true,"data":[{"sold_amount":1,"image":"/upload/20240108/3b186851020449f2a7986c0e86c10de1!460","favNumInfo":"人喜欢","price":388,"product_id":"668abdcd93f844d2a4cf38b1111c9a53","name":"【晒后补水】舒缓肌肤","market_price":588,"likeCount":381,"service_mode":0,"service_mode_value":"普通"},{"sold_amount":28,"image":"upload/20160615/33596aa4a86d465b9571c8ca42be6f32.png!460","favNumInfo":"人喜欢","price":496,"product_id":"3661a3db754b4ed8a50a3020619d877a","name":"「专业五星」肩颈＋背部＋腰部按摩","market_price":798,"likeCount":2731,"service_mode":0,"service_mode_value":"普通"},{"sold_amount":162,"image":"/upload/20221118/28831b3758504cc19192179524a6e6aa!460","favNumInfo":"人喜欢","price":358,"product_id":"576c71d504fc42a3b40009f5cd07517f","name":"【天鹅颈】颈部保养","market_price":698,"likeCount":7916,"service_mode":0,"service_mode_value":"普通"},{"sold_amount":1,"image":"upload/20160916/0f8d760f63cd458593ec010fe94ef8f4.jpg!460","favNumInfo":"人喜欢","price":398,"product_id":"3f5f62014c094e90bf38d0e21b5a037e","name":"肩颈～冬季热式美肩背按摩","market_price":698,"likeCount":838,"service_mode":0,"service_mode_value":"普通"},{"sold_amount":3,"image":"/upload/20200108/83864070f20f450691f0168673571423.JPG!460","favNumInfo":"人喜欢","price":598,"product_id":"768a6e0764e8470490b9aee189c1c3af","name":"腰肾保养〖调理腰肌劳损＆缓解腰酸胀疼+砭石驱寒补阳〗","market_price":598,"likeCount":1179,"service_mode":0,"service_mode_value":"普通"},{"sold_amount":0,"image":"/upload/20190518/0f30342babab4b8aa3063278dd2be0b4.jpg!460","favNumInfo":"人喜欢","price":168,"product_id":"1bf8b9c843d34048aa3d732017b6d35c","name":"冰点无痛腋下脱毛","market_price":990,"likeCount":3881,"service_mode":0,"service_mode_value":"普通"},{"sold_amount":24,"image":"/upload/20190701/ab8c1eeea2b14dee9a02e392b75c0c38!460","favNumInfo":"人喜欢","price":698,"product_id":"be2d3ccfb0534903ad63d96596d6234c","name":"【紧致提升抗衰】面眼颈拨筋提升+玻尿酸精华面膜送头部按摩","market_price":968,"likeCount":804,"service_mode":0,"service_mode_value":"普通"},{"sold_amount":382,"image":"upload/20170410/7aca81f0584942c89c35f547be7f067b.jpg!460","favNumInfo":"人喜欢","price":398,"product_id":"36f3c763575a47d39730358433145d85","name":"【痘肌调理】专业祛黑头清痘闭口","market_price":3280,"likeCount":17843,"service_mode":0,"service_mode_value":"普通"},{"sold_amount":8,"image":"/upload/20191017/410731313d774045a840448e6b62a2e8.JPG!460","favNumInfo":"人喜欢","price":359,"product_id":"572f93acb37043c6bd759af84a757d4c","name":"鲜活维C精华补水保湿抗氧化亮白护理","market_price":580,"likeCount":683,"service_mode":0,"service_mode_value":"普通"},{"sold_amount":35,"image":"/upload/20230208/088f5f19b363422c902f6c41ca5fa4a3.JPG!460","favNumInfo":"人喜欢","price":798,"product_id":"93d8183027a2464d8c113c067e782c49","name":"春季祛黄保湿+补水精华+射频仪美白透亮蛋壳肌","market_price":980,"likeCount":874,"service_mode":0,"service_mode_value":"普通"},{"sold_amount":0,"image":"/upload/20190614/93e96a3efb294628ba963ee3801481e7!460","favNumInfo":"人喜欢","price":368,"product_id":"9b95e14524c741a282008774bdc49b44","name":"套餐组合>肩颈舒缓+娇韵美胸","market_price":680,"likeCount":230,"service_mode":0,"service_mode_value":"普通"},{"sold_amount":2,"image":"/upload/20190930/fce40d50356341cf86510f3851a556f7.JPG!460","favNumInfo":"人喜欢","price":198,"product_id":"fb6ab0993c2b42968c8c79ff81c5ac1a","name":"头部按摩+ 头部拨筋","market_price":298,"likeCount":463,"service_mode":0,"service_mode_value":"普通"},{"sold_amount":4,"image":"/upload/20220901/7e1da012fe944a859827bfd779ce711b.JPG!460","favNumInfo":"人喜欢","price":198,"product_id":"9f72617d4a1546d0addded9ef403bb0a","name":"【橘皮鸡皮蛇皮滋养嫩滑】肝胆脾胃经调理美腿疏通","market_price":258,"likeCount":2488,"service_mode":0,"service_mode_value":"普通"},{"sold_amount":9,"image":"/upload/20200404/12ebc0b083af45f6a6f4a7a8131d60f3.JPG!460","favNumInfo":"人喜欢","price":458,"product_id":"99b2b8cf10a1488e8f94cb932b7c13ef","name":"<店长推荐>全身十二经络深度调理(90分钟)","market_price":598,"likeCount":1234,"service_mode":0,"service_mode_value":"普通"},{"sold_amount":12,"image":"/upload/20201011/7c3682d3547d44bb9550b433f37fd77e.JPG!460","favNumInfo":"人喜欢","price":318,"product_id":"cf3723ebc71544ed951b2ac7afd118a2","name":"全身经络疏通（背+腿+胸+胳膊）","market_price":598,"likeCount":695,"service_mode":0,"service_mode_value":"普通"},{"sold_amount":17,"image":"/upload/20230715/9160397076bc43fea41a1ea9f5256874!460","favNumInfo":"人喜欢","price":398,"product_id":"bb509bb6a51d44ebaf81d50197d7985f","name":"全身深度擀筋减压按摩肩+腰+腿+手臂","market_price":980,"likeCount":2497,"service_mode":0,"service_mode_value":"普通"},{"sold_amount":14,"image":"/upload/20200915/bb13821eb9154d2c9c4e38a2f2d874b5.JPG!460","favNumInfo":"人喜欢","price":622,"product_id":"7c024d7a983242a281d4f995465415c9","name":"【深度疏通】肩颈+腰背","market_price":668,"likeCount":1553,"service_mode":0,"service_mode_value":"普通"},{"sold_amount":6,"image":"/upload/20170726/853c45a2d3274b1ab37078c0190c606b!460","favNumInfo":"人喜欢","price":376,"product_id":"4b480f40605c4600bfd173b86609071a","name":"肩颈背部调理+颈侧淋巴+头部按摩","market_price":376,"likeCount":1350,"service_mode":0,"service_mode_value":"普通"},{"sold_amount":5,"image":"upload/20160703/f64402e409114ca18461c1a1e5757b8a.png!460","favNumInfo":"人喜欢","price":580,"product_id":"15ede5f38b024f22a4ac5a623e7c183b","name":"<油皮救星>小气泡清洁+收缩补水","market_price":880,"likeCount":791,"service_mode":0,"service_mode_value":"普通"},{"sold_amount":4,"image":"/upload/20180704/0ba27401fa3e466687959e97d0b85dbb!460","favNumInfo":"人喜欢","price":488,"product_id":"696e29687f0f4f15b4a82bd56eae5c06","name":"(舒胸健胸)健胸挺胸养护+腋下手臂","market_price":980,"likeCount":494,"service_mode":0,"service_mode_value":"普通"}],"process_time":518}